{
  "display": {
    "icon": {
      "item": "kamenridercraft:taddle_fantasy_gashat"
    },
    "title": "Final Fantasy",
    "description": "Obtain the Taddle Fantasy Gashat",
    "frame": "task",
    "show_toast": true,
    "announce_to_chat": true,
    "hidden": false
  },
  "parent": "kamenridercraft:ex-aid/brave",
  "criteria": {
    "requirement": {
      "trigger": "minecraft:inventory_changed",
      "conditions": {
        "player": [],
        "items": [
          {
            "items": [
              "kamenridercraft:taddle_fantasy_gashat"
            ]
          }
        ]
      }
    }
  }
}
